note/__init__.py
note/notebot.py
notebot-0.2.dist-info/METADATA
notebot-0.2.dist-info/WHEEL
notebot-0.2.dist-info/entry_points.txt
notebot-0.2.dist-info/top_level.txt
notebot-0.2.dist-info/RECORD
