Metadata-Version: 2.1
Name: notebot
Version: 0.2
Summary: A command-line tool to open Notepad or create and open files with Notepad.
Home-page: https://github.com/Tirthaboos/notebot
Author: Souporno Chakraborty
Author-email: shrabanichakraborty83@gmail.com
License: MIT
Keywords: notepad,file,command-line
